markus_pettersen/__init__.py
markus_pettersen/general.py
markus_pettersen/pd.py
markus_pettersen-0.1.1.dist-info/LICENSE
markus_pettersen-0.1.1.dist-info/METADATA
markus_pettersen-0.1.1.dist-info/WHEEL
markus_pettersen-0.1.1.dist-info/RECORD
